[
  {
    "Raw Transaction": "Transaction ID: TXN-2023-7C2D\nDate: 2023-08-15 14:25:00\n\nSender:\n\u2022 Name: \"Quantum Holdings Ltd\"\n\u2022 Account: VGB2BVIR024987654321 (British Virgin Islands)\n\u2022 Beneficiary Owner: \"Maria Gonzalez\" (DOB: 1975-04-12, Spanish passport ES789012)\n\u2022 home address: \"scottish road\"\n\u2022 extras: hehe\n\nReceiver:\n\u2022 Name: \"Golden Sands Trading EZE\"\n\u2022 Account: AE450330000012345678901 (Dubai, UAE)\n\u2022 Registration: UAE Free Zone License #789-F2\n\u2022 person: Hello\n\nAmount: $950,000.00 (USD)\nCurrency Exchange: EUR - USD (Rate: 1.12)\nTransaction Type: SWIFT\nReference: \"Commodity Trade Settlement - Contract #DX-889\"\n\nAdditional Notes:\n\u2022 \"Funds routed via Deutsche Bank Frankfurt (DEUTDEFE) - Emirates NBD/Dubai (EBILAEAD).\"\n\u2022 \"Approver: Mr. Viktor Petrov (Linked to OFAC SDN List entry 09876, 2022).\"\n\u2022 \"Invoice attached: '011 Equipment Procurement' (PDF missing metadata).\"",
    "Transaction ID": "TXN-2023-7C2D",
    "Date": "2023-08-15 14:25:00",
    "Amount": "950,000.00",
    "Currency Exchange": "EUR - USD (Rate: 1.12)\nTransaction Type: SWIFT\nReference: \"Commodity Trade Settlement - Contract #DX-889\"\n\nAdditional Notes:\n\u2022 \"Funds routed via Deutsche Bank Frankfurt (DEUTDEFE) - Emirates NBD/Dubai (EBILAEAD).\"\n\u2022 \"Approver: Mr. Viktor Petrov (Linked to OFAC SDN List entry 09876, 2022).\"\n\u2022 \"Invoice attached: '011 Equipment Procurement' (PDF missing metadata).\"",
    "Transaction Type": "SWIFT\nReference: \"Commodity Trade Settlement - Contract #DX-889\"\n\nAdditional Notes:\n\u2022 \"Funds routed via Deutsche Bank Frankfurt (DEUTDEFE) - Emirates NBD/Dubai (EBILAEAD).\"\n\u2022 \"Approver: Mr. Viktor Petrov (Linked to OFAC SDN List entry 09876, 2022).\"\n\u2022 \"Invoice attached: '011 Equipment Procurement' (PDF missing metadata).\"",
    "Reference": "Commodity Trade Settlement - Contract #DX-889\"\n\nAdditional Notes:\n\u2022 \"Funds routed via Deutsche Bank Frankfurt (DEUTDEFE) - Emirates NBD/Dubai (EBILAEAD).\"\n\u2022 \"Approver: Mr. Viktor Petrov (Linked to OFAC SDN List entry 09876, 2022).\"\n\u2022 \"Invoice attached: '011 Equipment Procurement' (PDF missing metadata).",
    "Sender": {
      "Name": "Quantum Holdings Ltd",
      "Account": "VGB2BVIR024987654321 (British Virgin Islands)",
      "Jurisdiction": "British Virgin Islands",
      "Additional Info": [
        "Beneficiary owner: Maria Gonzalez",
        "Home address: scottish road",
        "Extras: hehe"
      ]
    },
    "Receiver": {
      "Name": "Golden Sands Trading EZE",
      "Account": "AE450330000012345678901 (Dubai, UAE)",
      "Jurisdiction": "Dubai, UAE",
      "Additional Info": [
        "Registration: UAE Free Zone License #789-F2",
        "Person: Hello"
      ]
    },
    "Transaction Details": {
      "Notes": [
        "\u2022 \"Funds routed via Deutsche Bank Frankfurt (DEUTDEFE) - Emirates NBD/Dubai (EBILAEAD).\"",
        "\u2022 \"Approver: Mr. Viktor Petrov (Linked to OFAC SDN List entry 09876, 2022).\"",
        "\u2022 \"Invoice attached: '011 Equipment Procurement' (PDF missing metadata).\""
      ]
    },
    "Proper Noun Entities": [
      {
        "Entity Name": "Quantum Holdings Ltd",
        "Entity Type": "Organization"
      },
      {
        "Entity Name": "British Virgin Islands",
        "Entity Type": "Jurisdiction"
      },
      {
        "Entity Name": "Maria Gonzalez",
        "Entity Type": "Person"
      },
      {
        "Entity Name": "Dubai",
        "Entity Type": "Jurisdiction"
      },
      {
        "Entity Name": "Deutsche Bank",
        "Entity Type": "Organization"
      },
      {
        "Entity Name": "Frankfurt",
        "Entity Type": "Jurisdiction"
      },
      {
        "Entity Name": "Viktor Petrov",
        "Entity Type": "Person"
      }
    ]
  }
]
